pvfactors/__init__.py
pvfactors/_version.py
pvfactors/config.py
pvfactors/engine.py
pvfactors/report.py
pvfactors/run.py
pvfactors/version.py
pvfactors/geometry/__init__.py
pvfactors/geometry/base.py
pvfactors/geometry/plot.py
pvfactors/geometry/pvarray.py
pvfactors/geometry/pvground.py
pvfactors/geometry/pvrow.py
pvfactors/geometry/timeseries.py
pvfactors/geometry/utils.py
pvfactors/irradiance/__init__.py
pvfactors/irradiance/base.py
pvfactors/irradiance/models.py
pvfactors/irradiance/utils.py
pvfactors/viewfactors/__init__.py
pvfactors/viewfactors/aoimethods.py
pvfactors/viewfactors/calculator.py
pvfactors/viewfactors/vfmethods.py
pvfactors-1.5.2.dist-info/LICENSE
pvfactors-1.5.2.dist-info/METADATA
pvfactors-1.5.2.dist-info/WHEEL
pvfactors-1.5.2.dist-info/top_level.txt
pvfactors-1.5.2.dist-info/RECORD
