Metadata-Version: 2.1
Name: pvfactors
Version: 1.5.2
Summary: 2D View Factor Model to calculate the irradiance incident on various surfaces of PV arrays
Home-page: https://github.com/SunPower/pvfactors
Author: SunPower
Maintainer-email: marc.abouanoma@sunpowercorp.com
License: BSD 3-Clause
Platform: UNKNOWN
Classifier: Development Status :: 3 - Alpha
Classifier: License :: OSI Approved :: BSD License
Classifier: Operating System :: OS Independent
Classifier: Intended Audience :: Science/Research
Classifier: Programming Language :: Python
Classifier: Programming Language :: Python :: 3.6
Classifier: Programming Language :: Python :: 3.7
Classifier: Programming Language :: Python :: 3.8
Classifier: Programming Language :: Python :: 3.9
Classifier: Topic :: Scientific/Engineering
License-File: LICENSE
Requires-Dist: pvlib (<0.10.0,>=0.9.0)
Requires-Dist: shapely (<2,>=1.6.4.post2)
Requires-Dist: matplotlib
Requires-Dist: future
Requires-Dist: six
Provides-Extra: docs
Requires-Dist: Sphinx (~=4.0) ; extra == 'docs'
Requires-Dist: sphinx-rtd-theme ; extra == 'docs'
Requires-Dist: nbsphinx ; extra == 'docs'
Requires-Dist: sphinxcontrib-napoleon ; extra == 'docs'
Requires-Dist: sphinxcontrib-github-alt ; extra == 'docs'
Requires-Dist: ipykernel ; extra == 'docs'
Provides-Extra: testing
Requires-Dist: pytest (>=3.2.1) ; extra == 'testing'
Requires-Dist: pytest-mock (>=1.10.0) ; extra == 'testing'
Requires-Dist: mock ; extra == 'testing'
